kitconcept.contentcreator-5.1.0-py3.8-nspkg.pth
kitconcept/contentcreator/Poppins-Regular.ttf
kitconcept/contentcreator/__init__.py
kitconcept/contentcreator/configure.zcml
kitconcept/contentcreator/creator.py
kitconcept/contentcreator/dummy_image.py
kitconcept/contentcreator/images.py
kitconcept/contentcreator/interfaces.py
kitconcept/contentcreator/scales.py
kitconcept/contentcreator/testing.py
kitconcept/contentcreator/translations.py
kitconcept/contentcreator/utils.py
kitconcept/contentcreator/tests/__init__.py
kitconcept/contentcreator/tests/fields_blocks.json
kitconcept/contentcreator/tests/fields_file.json
kitconcept/contentcreator/tests/fields_image.json
kitconcept/contentcreator/tests/image.png
kitconcept/contentcreator/tests/image.svg
kitconcept/contentcreator/tests/report.pdf
kitconcept/contentcreator/tests/test_adapters.py
kitconcept/contentcreator/tests/test_content.json
kitconcept/contentcreator/tests/test_creation.py
kitconcept/contentcreator/tests/alternate/a-folder.a-document-1.json
kitconcept/contentcreator/tests/content/a-folder.a-document-1.json
kitconcept/contentcreator/tests/content/a-folder.a-document-2.json
kitconcept/contentcreator/tests/content/a-folder.a-document-3.json
kitconcept/contentcreator/tests/content/a-folder.a-link.json
kitconcept/contentcreator/tests/content/a-folder.the-last-document.json
kitconcept/contentcreator/tests/content/content.json
kitconcept/contentcreator/tests/content/siteroot.json
kitconcept/contentcreator/tests/content_with_refresh/content.json
kitconcept/contentcreator/tests/content_with_translations/de.seite.json
kitconcept/contentcreator/tests/content_with_translations/en.page.json
kitconcept/contentcreator/tests/content_with_translations/translations.csv
kitconcept.contentcreator-5.1.0.dist-info/METADATA
kitconcept.contentcreator-5.1.0.dist-info/WHEEL
kitconcept.contentcreator-5.1.0.dist-info/entry_points.txt
kitconcept.contentcreator-5.1.0.dist-info/namespace_packages.txt
kitconcept.contentcreator-5.1.0.dist-info/top_level.txt
kitconcept.contentcreator-5.1.0.dist-info/RECORD
