Metadata-Version: 2.1
Name: kitconcept.contentcreator
Version: 5.1.0
Summary: Create Plone content via JSON
Home-page: https://github.com/kitconcept/kitconcept.contentcreator
Author: kitconcept GmbH
Author-email: info@kitconcept.com
License: GPL version 2
Keywords: Python Plone
Classifier: Environment :: Web Environment
Classifier: Framework :: Plone
Classifier: Framework :: Plone :: 5.2
Classifier: Framework :: Plone :: 6.0
Classifier: Programming Language :: Python
Classifier: Programming Language :: Python :: 3 :: Only
Classifier: Programming Language :: Python :: 3.8
Classifier: Programming Language :: Python :: 3.9
Classifier: Operating System :: OS Independent
Classifier: Development Status :: 6 - Mature
Classifier: License :: OSI Approved :: GNU General Public License v2 (GPLv2)
Requires-Dist: kitconcept.api
Requires-Dist: plone.restapi (>=7.5.0)
Requires-Dist: Products.GenericSetup
Requires-Dist: setuptools
Requires-Dist: python-magic
Provides-Extra: test
Requires-Dist: plone.app.testing ; extra == 'test'
Requires-Dist: plone.testing ; extra == 'test'
Requires-Dist: plone.app.contenttypes ; extra == 'test'
Requires-Dist: plone.app.multilingual ; extra == 'test'
Requires-Dist: plone.app.robotframework[debug] ; extra == 'test'
